django_migralign/__init__.py
django_migralign/apps.py
django_migralign/management/commands/helper.py
django_migralign/management/commands/migralign.py
django_migralign-1.0.0.dist-info/LICENSE
django_migralign-1.0.0.dist-info/METADATA
django_migralign-1.0.0.dist-info/WHEEL
django_migralign-1.0.0.dist-info/top_level.txt
django_migralign-1.0.0.dist-info/RECORD
