Metadata-Version: 2.1
Name: django_migralign
Version: 1.0.0
Summary: Ensure your migrations are linear across environments.
Author-email: Amr Elsayed <elsayed.amr50@gmail.com>
License: MIT
Project-URL: Repository, https://github.com/AmrElsayedEG/django_migralign
Keywords: Django
Requires-Python: >=2.7
License-File: LICENSE
